<?xml version="1.0" encoding="utf-8" standalone="no"?>
<epp xmlns="urn:ietf:params:xml:ns:epp-1.0">
  <response>
    <result code="1000">
      <msg>Command completed successfully</msg>
    </result>
    <resData>
      <domain:chkData
        xmlns:domain="urn:ietf:params:xml:ns:domain-1.0">
        <domain:cd>
          <domain:name avail="1">example.com</domain:name>
        </domain:cd>
        <domain:cd>
          <domain:name avail="0">example.net</domain:name>
          <domain:reason>In use</domain:reason>
        </domain:cd>
        <domain:cd>
          <domain:name avail="0">example.org</domain:name>
          <domain:reason>In use</domain:reason>
        </domain:cd>
      </domain:chkData>
    </resData>
    <extension>
      <fee:chkData
        xmlns:fee="urn:ietf:params:xml:ns:fee-0.5">
        <fee:cd
          xmlns:fee="urn:ietf:params:xml:ns:fee-0.5">
          <fee:name>example.com</fee:name>
          <fee:currency>USD</fee:currency>
          <fee:command phase="sunrise">create</fee:command>
          <fee:period unit="y">1</fee:period>
          <fee:fee description="Application Fee">5.00</fee:fee>
          <fee:fee description="Registration Fee">5.00</fee:fee>
        </fee:cd>
        <fee:cd
          xmlns:fee="urn:ietf:params:xml:ns:fee-0.5">
          <fee:name>example.net</fee:name>
          <fee:currency>EUR</fee:currency>
          <fee:command phase="claims" subphase="landrush">
          create</fee:command>
          <fee:period unit="y">2</fee:period>
          <fee:fee>5.00</fee:fee>
        </fee:cd>
        <fee:cd
          xmlns:fee="urn:ietf:params:xml:ns:fee-0.5">
          <fee:name>example.org</fee:name>
          <fee:currency>EUR</fee:currency>
          <fee:command>transfer</fee:command>
          <fee:period unit="y">2</fee:period>
          <fee:fee description="Transfer Fee">2.50</fee:fee>
          <fee:fee description="Renewal Fee">10.00</fee:fee>
        </fee:cd>
        <fee:cd
          xmlns:fee="urn:ietf:params:xml:ns:fee-0.5">
          <fee:name premium="1">example.xyz</fee:name>
          <fee:currency>GBP</fee:currency>
          <fee:command>restore</fee:command>
          <fee:period unit="y">1</fee:period>
          <fee:fee description="Restore Fee">25</fee:fee>
          <fee:fee description="Renewal Fee">5.00</fee:fee>
        </fee:cd>
      </fee:chkData>
    </extension>
    <trID>
      <clTRID>ABC-12345</clTRID>
      <svTRID>54322-XYZ</svTRID>
    </trID>
  </response>
</epp>
